pycatchmod/__init__.py
pycatchmod/__main__.py
pycatchmod/_catchmod.cp36-win_amd64.pyd
pycatchmod/_weather_generator.cp36-win_amd64.pyd
pycatchmod/weather_generator.py
pycatchmod/io/__init__.py
pycatchmod/io/excel.py
pycatchmod/io/json.py
pycatchmod-1.1.0.dist-info/METADATA
pycatchmod-1.1.0.dist-info/RECORD
pycatchmod-1.1.0.dist-info/WHEEL
pycatchmod-1.1.0.dist-info/entry_points.txt
pycatchmod-1.1.0.dist-info/top_level.txt
