Metadata-Version: 2.1
Name: pycatchmod
Version: 1.1.0
Summary: Python implementation of the rainfall runoff model CATCHMOD.
Home-page: UNKNOWN
Author: James E Tomlinson
Author-email: tomo.bbe@gmail.com
License: UNKNOWN
Platform: UNKNOWN
